sceptr/__init__.py
sceptr/model.py
sceptr/variant.py
sceptr/_model_saves/__init__.py
sceptr/_model_saves/A_SCEPTR/config.json
sceptr/_model_saves/A_SCEPTR/log.csv
sceptr/_model_saves/A_SCEPTR/state_dict.pt
sceptr/_model_saves/B_SCEPTR/config.json
sceptr/_model_saves/B_SCEPTR/log.csv
sceptr/_model_saves/B_SCEPTR/state_dict.pt
sceptr/_model_saves/SCEPTR/config.json
sceptr/_model_saves/SCEPTR/log.csv
sceptr/_model_saves/SCEPTR/state_dict.pt
sceptr/_model_saves/SCEPTR_BLOSUM/config.json
sceptr/_model_saves/SCEPTR_BLOSUM/log.csv
sceptr/_model_saves/SCEPTR_BLOSUM/state_dict.pt
sceptr/_model_saves/SCEPTR_CDR3_only/config.json
sceptr/_model_saves/SCEPTR_CDR3_only/log.csv
sceptr/_model_saves/SCEPTR_CDR3_only/state_dict.pt
sceptr/_model_saves/SCEPTR_CDR3_only_MLM_only/config.json
sceptr/_model_saves/SCEPTR_CDR3_only_MLM_only/log.csv
sceptr/_model_saves/SCEPTR_CDR3_only_MLM_only/state_dict.pt
sceptr/_model_saves/SCEPTR_MLM_only/config.json
sceptr/_model_saves/SCEPTR_MLM_only/log.csv
sceptr/_model_saves/SCEPTR_MLM_only/state_dict.pt
sceptr/_model_saves/SCEPTR_average_pooling/config.json
sceptr/_model_saves/SCEPTR_average_pooling/log.csv
sceptr/_model_saves/SCEPTR_average_pooling/state_dict.pt
sceptr/_model_saves/SCEPTR_dropout_noise_only/config.json
sceptr/_model_saves/SCEPTR_dropout_noise_only/log.csv
sceptr/_model_saves/SCEPTR_dropout_noise_only/state_dict.pt
sceptr/_model_saves/SCEPTR_finetuned/config.json
sceptr/_model_saves/SCEPTR_finetuned/log.csv
sceptr/_model_saves/SCEPTR_finetuned/state_dict.pt
sceptr/_model_saves/SCEPTR_large/config.json
sceptr/_model_saves/SCEPTR_large/log.csv
sceptr/_model_saves/SCEPTR_large/state_dict.pt
sceptr/_model_saves/SCEPTR_left_aligned/config.json
sceptr/_model_saves/SCEPTR_left_aligned/log.csv
sceptr/_model_saves/SCEPTR_left_aligned/state_dict.pt
sceptr/_model_saves/SCEPTR_shuffled_data/config.json
sceptr/_model_saves/SCEPTR_shuffled_data/log.csv
sceptr/_model_saves/SCEPTR_shuffled_data/state_dict.pt
sceptr-1.2.0.dist-info/licenses/LICENSE.txt
sceptr-1.2.0.dist-info/METADATA
sceptr-1.2.0.dist-info/WHEEL
sceptr-1.2.0.dist-info/top_level.txt
sceptr-1.2.0.dist-info/RECORD
