Metadata-Version: 2.4
Name: sceptr
Version: 1.2.0
Summary: Fast and performant TCR representation model
Author-email: Yuta Nagano <yutanagano51@proton.me>
Maintainer-email: Yuta Nagano <yutanagano51@proton.me>
Project-URL: Homepage, https://sceptr.readthedocs.io
Project-URL: Documentation, https://sceptr.readthedocs.io
Project-URL: Repository, https://github.com/yutanagano/sceptr
Project-URL: Issues, https://github.com/yutanagano/sceptr/issues
Keywords: TCR,TR,T cell,transformer,bert,MLM,immunology,bioinformatics
Classifier: Development Status :: 5 - Production/Stable
Classifier: Intended Audience :: Science/Research
Classifier: License :: OSI Approved :: MIT License
Classifier: Operating System :: OS Independent
Classifier: Programming Language :: Python :: 3
Classifier: Topic :: Scientific/Engineering
Requires-Python: >=3.9
License-File: LICENSE.txt
Requires-Dist: libtcrlm~=1.0
Requires-Dist: numpy~=2.0
Requires-Dist: pandas~=2.0
Requires-Dist: torch~=2.0
Provides-Extra: dev
Requires-Dist: pytest; extra == "dev"
Requires-Dist: pytest-cov; extra == "dev"
Requires-Dist: tox; extra == "dev"
Requires-Dist: sphinx; extra == "dev"
Requires-Dist: sphinx_book_theme; extra == "dev"
Provides-Extra: docs
Requires-Dist: sphinx_book_theme; extra == "docs"
Dynamic: license-file
